{"value":{"$size":467,"size":467,"genres":{"$size":467,"size":467,"39960":{"$size":1,"size":1,"name":"Inspiring Independent Social Issue Dramas"},"39961":{"$size":1,"size":1,"name":"Gory Suspenseful Movies from the 1970s"},"39964":{"$size":1,"size":1,"name":"Critically-acclaimed Gritty Thrillers on Blu-ray"},"39969":{"$size":1,"size":1,"name":"Gritty Foreign Dramas on Blu-ray"},"39975":{"$size":1,"size":1,"name":"Cerebral Fight-the-System Movies on Blu-ray"},"39977":{"$size":1,"size":1,"name":"Emotional Foreign Military Dramas"},"39978":{"$size":1,"size":1,"name":"Witty Buddy TV Dramas"},"39982":{"$size":1,"size":1,"name":"Australian Serial-Killer Movies"},"39988":{"$size":1,"size":1,"name":"Gory Cult Action & Adventure"},"39989":{"$size":1,"size":1,"name":"Movies directed by Danny Boyle"},"39991":{"$size":1,"size":1,"name":"Inspiring Courtroom Social Issue Dramas"},"39992":{"$size":1,"size":1,"name":"Gory College Horror Movies"},"39998":{"$size":1,"size":1,"name":"Critically-acclaimed Gritty Father-Son Relationship Movies"},"39999":{"$size":1,"size":1,"name":"Cerebral Foreign Showbiz Movies"},"40001":{"$size":1,"size":1,"name":"Gory Serial-Killer Movies based on real life"},"40004":{"$size":1,"size":1,"name":"Gory Alien Sci-Fi from the 1980s"},"40006":{"$size":1,"size":1,"name":"Gory Serial-Killer Action & Adventure"},"40007":{"$size":1,"size":1,"name":"Cerebral Foreign Father-Daughter Relationship Dramas"},"40008":{"$size":1,"size":1,"name":"Raunchy Crime Comedies from the 1980s"},"40014":{"$size":1,"size":1,"name":"Critically-acclaimed Mother-Daughter Relationship Movies on Blu-ray"},"40017":{"$size":1,"size":1,"name":"Visually-striking Independent Dramas from the 1980s"},"40020":{"$size":1,"size":1,"name":"Critically-acclaimed Foreign Workplace Movies"},"40021":{"$size":1,"size":1,"name":"Gory Post-Apocalypse Horror Movies"},"40023":{"$size":1,"size":1,"name":"Visually-striking Gritty Independent Crime Movies"},"40024":{"$size":1,"size":1,"name":"Gory Crime TV Programmes"},"40026":{"$size":1,"size":1,"name":"Gory Suspenseful Movies based on real life"},"40028":{"$size":1,"size":1,"name":"Cerebral Foreign Movies on Blu-ray from the 1960s"},"40033":{"$size":1,"size":1,"name":"Gory Sci-Fi Adventure"},"40034":{"$size":1,"size":1,"name":"Gory Ghost-story Movies on Blu-ray"},"40042":{"$size":1,"size":1,"name":"Gritty Foreign Serial-Killer Movies"},"40046":{"$size":1,"size":1,"name":"Controversial TV Programmes"},"40047":{"$size":1,"size":1,"name":"Controversial Military Documentaries"},"40048":{"$size":1,"size":1,"name":"Steamy Independent Dramas on Blu-ray"},"40051":{"$size":1,"size":1,"name":"Critically-acclaimed Gritty Military Movies on Blu-ray"},"40052":{"$size":1,"size":1,"name":"Quirky Romantic Independent Movies on Blu-ray"},"40054":{"$size":1,"size":1,"name":"Gritty Movies starring Al Pacino"},"40057":{"$size":1,"size":1,"name":"Cerebral Political Comedies"},"40058":{"$size":1,"size":1,"name":"Exciting TV Documentaries"},"40059":{"$size":1,"size":1,"name":"Critically-acclaimed Quirky Father-Son Relationship Movies"},"40065":{"$size":1,"size":1,"name":"Raunchy Independent Comedies on Blu-ray"},"40067":{"$size":1,"size":1,"name":"Adult Animation from the 1970s"},"40068":{"$size":1,"size":1,"name":"Cerebral British Political Dramas"},"40070":{"$size":1,"size":1,"name":"Action & Adventure starring Audie Murphy"},"40072":{"$size":1,"size":1,"name":"Imaginative Comic Book and Superhero Movies on Blu-ray"},"40073":{"$size":1,"size":1,"name":"Exciting TV Shows from the 1960s"},"40075":{"$size":1,"size":1,"name":"Imaginative Talking-Animal Animation on Blu-ray"},"40078":{"$size":1,"size":1,"name":"Emotional Independent Dramas from the 1980s"},"40080":{"$size":1,"size":1,"name":"Witty Reality TV"},"40081":{"$size":1,"size":1,"name":"Gritty Basketball Movies"},"40083":{"$size":1,"size":1,"name":"Witty Showbiz TV Sketch Comedies"},"40084":{"$size":1,"size":1,"name":"Critically-acclaimed Cerebral Military Documentaries"},"40085":{"$size":1,"size":1,"name":"Cerebral Conspiracy Movies on Blu-ray"},"40088":{"$size":1,"size":1,"name":"LGBT Biographical 20th Century Period Pieces"},"40089":{"$size":1,"size":1,"name":"Imaginative Sci-Fi Adventure for ages 11 to 12"},"40090":{"$size":1,"size":1,"name":"Emotional Political Dramas on Blu-ray"},"40091":{"$size":1,"size":1,"name":"Gritty TV Documentaries"},"40094":{"$size":1,"size":1,"name":"Imaginative End-of-the-World Movies"},"40095":{"$size":1,"size":1,"name":"Cerebral Independent Dysfunctional-Family Dramas"},"40096":{"$size":1,"size":1,"name":"Imaginative Sci-Fi Adventure for ages 8 to 10"},"40098":{"$size":1,"size":1,"name":"Imaginative End-of-the-World Sci-Fi & Fantasy"},"40100":{"$size":1,"size":1,"name":"Imaginative Animation on Blu-ray for ages 11 to 12"},"40103":{"$size":1,"size":1,"name":"Visually-striking Imaginative Alien Sci-Fi on Blu-ray"},"40104":{"$size":1,"size":1,"name":"Critically-acclaimed Prison Movies on Blu-ray"},"40109":{"$size":1,"size":1,"name":"Critically-acclaimed Imaginative Action & Adventure"},"40113":{"$size":1,"size":1,"name":"Controversial TV Documentaries"},"40114":{"$size":1,"size":1,"name":"Inspiring Soccer Movies"},"40119":{"$size":1,"size":1,"name":"Critically-acclaimed Imaginative Comedies"},"40120":{"$size":1,"size":1,"name":"Goofy Cult B-Horror Movies"},"40124":{"$size":1,"size":1,"name":"Imaginative Underdog Children & Family Movies"},"40127":{"$size":1,"size":1,"name":"Exciting Sports TV Programmes"},"40128":{"$size":1,"size":1,"name":"Critically-acclaimed Conspiracy Movies on Blu-ray"},"40130":{"$size":1,"size":1,"name":"Critically-acclaimed Imaginative Movies from the 1980s"},"40131":{"$size":1,"size":1,"name":"Understated Romantic Independent Coming-of-age Dramas"},"40132":{"$size":1,"size":1,"name":"Inspiring Biographical Fight-the-System Documentaries"},"40136":{"$size":1,"size":1,"name":"Cerebral Documentaries on Blu-ray"},"40137":{"$size":1,"size":1,"name":"Emotional Movies on Blu-ray from the 1980s"},"40138":{"$size":1,"size":1,"name":"Imaginative Underdog Movies on Blu-ray"},"40143":{"$size":1,"size":1,"name":"Visually-striking Imaginative Sci-Fi Adventure"},"40144":{"$size":1,"size":1,"name":"Quirky Buddy Movies on Blu-ray"},"40145":{"$size":1,"size":1,"name":"Violent Suspenseful Foreign Revenge Movies"},"40147":{"$size":1,"size":1,"name":"Understated Military Dramas based on real life"},"40153":{"$size":1,"size":1,"name":"Critically-acclaimed Japanese Movies from the 1950s"},"40154":{"$size":1,"size":1,"name":"Imaginative Fairy Tale Animation for ages 5 to 7"},"40155":{"$size":1,"size":1,"name":"Heartfelt Independent Mother-Son Relationship Movies"},"40156":{"$size":1,"size":1,"name":"Exciting Romantic Movies on Blu-ray"},"40158":{"$size":1,"size":1,"name":"Goofy TV Sci-Fi & Fantasy from the 1980s"},"40161":{"$size":1,"size":1,"name":"Controversial Showbiz Movies"},"40162":{"$size":1,"size":1,"name":"Witty TV Shows on Blu-ray"},"40163":{"$size":1,"size":1,"name":"Visually-striking Imaginative Adventures"},"40164":{"$size":1,"size":1,"name":"Action & Adventure starring Dean Cain"},"40166":{"$size":1,"size":1,"name":"Emotional Period Pieces from the 1980s"},"40168":{"$size":1,"size":1,"name":"Cerebral Biographical Movies on Blu-ray"},"40169":{"$size":1,"size":1,"name":"Understated LGBT Biographical Movies"},"40170":{"$size":1,"size":1,"name":"Imaginative Father-Son Relationship Children & Family Movies"},"40173":{"$size":1,"size":1,"name":"Understated Independent Mid-Life-Crisis Dramas"},"40176":{"$size":1,"size":1,"name":"Imaginative Animation from the 1980s"},"40177":{"$size":1,"size":1,"name":"Understated Independent Mysteries"},"40180":{"$size":1,"size":1,"name":"Imaginative Sci-Fi Dramas"},"40183":{"$size":1,"size":1,"name":"Imaginative Animation on Blu-ray for ages 5 to 7"},"40184":{"$size":1,"size":1,"name":"Imaginative Space-Travel Movies from the 1980s"},"40187":{"$size":1,"size":1,"name":"Imaginative Sci-Fi Adventure on Blu-ray"},"40189":{"$size":1,"size":1,"name":"Visually-striking Witty Comedies on Blu-ray"},"40192":{"$size":1,"size":1,"name":"Cerebral Independent Father-Son Relationship Dramas"},"40193":{"$size":1,"size":1,"name":"Imaginative Action & Adventure for ages 8 to 10"},"40195":{"$size":1,"size":1,"name":"Emotional TV Soaps"},"40198":{"$size":1,"size":1,"name":"Cerebral Dramas based on real life from the 1980s"},"40199":{"$size":1,"size":1,"name":"Cerebral TV Documentaries"},"40200":{"$size":1,"size":1,"name":"Witty Mother-Daughter Relationship TV Shows"},"40203":{"$size":1,"size":1,"name":"Campy Mad-Scientist TV Shows"},"40204":{"$size":1,"size":1,"name":"Controversial Spiritual Documentaries"},"40210":{"$size":1,"size":1,"name":"Imaginative Satires"},"40211":{"$size":1,"size":1,"name":"Imaginative Comedies from the 1980s"},"40213":{"$size":1,"size":1,"name":"Imaginative Alien Sci-Fi on Blu-ray"},"40214":{"$size":1,"size":1,"name":"Imaginative Adult Animation"},"40215":{"$size":1,"size":1,"name":"Quirky Buddy TV Shows"},"40216":{"$size":1,"size":1,"name":"Imaginative Talking-Animal Animation for ages 8 to 10"},"40217":{"$size":1,"size":1,"name":"Emotional TV Programmes Featuring a Strong Female Lead"},"40219":{"$size":1,"size":1,"name":"Dysfunctional-Family Slasher and Serial Killer Movies"},"40220":{"$size":1,"size":1,"name":"Visually-striking Emotional Sci-Fi & Fantasy"},"40222":{"$size":1,"size":1,"name":"Visually-striking Imaginative Talking-Animal Movies"},"40223":{"$size":1,"size":1,"name":"Visually-striking Quirky Comedies on Blu-ray"},"40224":{"$size":1,"size":1,"name":"Heartfelt Military Historical Documentaries"},"40229":{"$size":1,"size":1,"name":"Campy TV Sci-Fi & Fantasy from the 1980s"},"40230":{"$size":1,"size":1,"name":"Controversial Cult Movies"},"40232":{"$size":1,"size":1,"name":"Imaginative Adventures on Blu-ray"},"40233":{"$size":1,"size":1,"name":"Critically-acclaimed Emotional Fight-the-System Dramas"},"40234":{"$size":1,"size":1,"name":"Imaginative Conspiracy Sci-Fi & Fantasy"},"40235":{"$size":1,"size":1,"name":"Imaginative Post-Apocalypse Movies"},"40236":{"$size":1,"size":1,"name":"Visually-striking Imaginative Alien Sci-Fi"},"40240":{"$size":1,"size":1,"name":"Exciting Reality TV"},"40243":{"$size":1,"size":1,"name":"Dark Conspiracy Action & Adventure"},"40247":{"$size":1,"size":1,"name":"Cerebral Sports Movies"},"40251":{"$size":1,"size":1,"name":"Understated Suspenseful TV Dramas"},"40252":{"$size":1,"size":1,"name":"Gory Suspenseful Viral Plague Movies"},"40253":{"$size":1,"size":1,"name":"Goofy Horror Movies on Blu-ray"},"40254":{"$size":1,"size":1,"name":"Cerebral 20th Century Period Pieces on Blu-ray"},"40255":{"$size":1,"size":1,"name":"Witty Space-Travel TV Comedies"},"40259":{"$size":1,"size":1,"name":"Emotional TV Dramas about Marriage"},"40261":{"$size":1,"size":1,"name":"Critically-acclaimed Imaginative Animation on Blu-ray"},"40262":{"$size":1,"size":1,"name":"Quirky TV Animated Comedies"},"40263":{"$size":1,"size":1,"name":"Heartfelt Independent Tearjerkers"},"40264":{"$size":1,"size":1,"name":"Imaginative Space-Travel TV Shows"},"40266":{"$size":1,"size":1,"name":"Cerebral Independent Father-Son Relationship Movies"},"40267":{"$size":1,"size":1,"name":"Witty TV Sketch Comedies from the 1970s"},"40268":{"$size":1,"size":1,"name":"Imaginative Post-Apocalypse Sci-Fi & Fantasy"},"40270":{"$size":1,"size":1,"name":"Gory Suspenseful Mad-Scientist Movies"},"40271":{"$size":1,"size":1,"name":"Imaginative Adventures from the 1980s"},"40272":{"$size":1,"size":1,"name":"Imaginative Talking-Animal Films for ages 11 to 12"},"40276":{"$size":1,"size":1,"name":"Visually-striking Imaginative Suspenseful Movies"},"40277":{"$size":1,"size":1,"name":"Action & Adventure starring Rock Hudson"},"40278":{"$size":1,"size":1,"name":"Witty Suspenseful Action & Adventure"},"40284":{"$size":1,"size":1,"name":"Goofy Mad-Scientist TV Shows"},"40285":{"$size":1,"size":1,"name":"Action Sci-Fi & Fantasy on Blu-ray from the 1970s"},"40287":{"$size":1,"size":1,"name":"Imaginative Conspiracy Films"},"40288":{"$size":1,"size":1,"name":"Feel-good Family Dramas on Blu-ray"},"40294":{"$size":1,"size":1,"name":"Cerebral British Dramas on Blu-ray"},"40295":{"$size":1,"size":1,"name":"Understated British Movies from the 1980s"},"40297":{"$size":1,"size":1,"name":"Biographical Showbiz Movies on Blu-ray"},"40298":{"$size":1,"size":1,"name":"Imaginative Suspenseful Action Sci-Fi & Fantasy"},"40300":{"$size":1,"size":1,"name":"Imaginative Sci-Fi Adventure from the 1980s"},"40301":{"$size":1,"size":1,"name":"Goofy Foreign Mistaken-Identity Comedies"},"40302":{"$size":1,"size":1,"name":"Understated Romantic Independent First-Love Dramas"},"40304":{"$size":1,"size":1,"name":"Imaginative Fairy Tale Animation for ages 8 to 10"},"40306":{"$size":1,"size":1,"name":"Visually-striking Imaginative Sci-Fi Thrillers"},"40307":{"$size":1,"size":1,"name":"Visually-striking Imaginative Space-Travel Movies"},"40308":{"$size":1,"size":1,"name":"Understated British Political Movies"},"40311":{"$size":1,"size":1,"name":"Imaginative Animation on Blu-ray for ages 8 to 10"},"40314":{"$size":1,"size":1,"name":"Cerebral Romantic Dramas on Blu-ray"},"40315":{"$size":1,"size":1,"name":"Goofy Foreign Mistaken-Identity Movies"},"40317":{"$size":1,"size":1,"name":"Imaginative Space-Travel Movies on Blu-ray"},"40319":{"$size":1,"size":1,"name":"Scary Suspenseful Viral Plague Sci-Fi & Fantasy"},"40320":{"$size":1,"size":1,"name":"Exciting Military Action Sci-Fi & Fantasy"},"40322":{"$size":1,"size":1,"name":"Workplace Social & Cultural Documentaries"},"40325":{"$size":1,"size":1,"name":"Visually-striking Mistaken-Identity Movies"},"40328":{"$size":1,"size":1,"name":"Inspiring British Dramas based on real life"},"40329":{"$size":1,"size":1,"name":"Heartfelt 20th Century Period Pieces from the 1980s"},"40333":{"$size":1,"size":1,"name":"Romantic Independent Mid-Life-Crisis Dramas"},"40335":{"$size":1,"size":1,"name":"Imaginative Talking-Animal Animation for ages 5 to 7"},"40336":{"$size":1,"size":1,"name":"Witty British Dramas from the 1980s"},"40337":{"$size":1,"size":1,"name":"Imaginative Sci-Fi Thrillers on Blu-ray"},"40338":{"$size":1,"size":1,"name":"Cerebral Dramas on Blu-ray from the 1980s"},"40339":{"$size":1,"size":1,"name":"Exciting TV Shows from the 1970s"},"40340":{"$size":1,"size":1,"name":"Cerebral Biographical Dramas from the 1980s"},"40341":{"$size":1,"size":1,"name":"Imaginative Cult Sci-Fi & Fantasy"},"40342":{"$size":1,"size":1,"name":"Imaginative Horror Films"},"40343":{"$size":1,"size":1,"name":"Emotional TV Dramas Featuring a Strong Female Lead"},"40346":{"$size":1,"size":1,"name":"Cerebral Crime Social & Cultural Documentaries"},"40347":{"$size":1,"size":1,"name":"Independent Dysfunctional-Family Tearjerkers"},"40349":{"$size":1,"size":1,"name":"Visually-striking Cerebral Sci-Fi & Fantasy on Blu-ray"},"40350":{"$size":1,"size":1,"name":"Violent Suspenseful Military Action & Adventure"},"40351":{"$size":1,"size":1,"name":"Critically-acclaimed Gritty Crime Thrillers on Blu-ray"},"40352":{"$size":1,"size":1,"name":"Heartfelt Period Pieces based on classic literature"},"40354":{"$size":1,"size":1,"name":"Controversial Crime Documentaries"},"40355":{"$size":1,"size":1,"name":"Cult Sports Comedies"},"40356":{"$size":1,"size":1,"name":"Emotional Crime Social & Cultural Documentaries"},"40363":{"$size":1,"size":1,"name":"Imaginative TV Action & Adventure"},"40364":{"$size":1,"size":1,"name":"Spy Adventures"},"40366":{"$size":1,"size":1,"name":"Goofy Spy Movies from the 1960s"},"40367":{"$size":1,"size":1,"name":"Films directed by Leslie Small"},"40370":{"$size":1,"size":1,"name":"Critically-acclaimed Sentimental British Movies"},"40371":{"$size":1,"size":1,"name":"Spy Thrillers from the 1940s"},"40372":{"$size":1,"size":1,"name":"Cerebral 20th Century Period Pieces from the 1980s"},"40374":{"$size":1,"size":1,"name":"Independent Psychological Movies on Blu-ray"},"40377":{"$size":1,"size":1,"name":"Movies directed by Alex Cox"},"40380":{"$size":1,"size":1,"name":"Buddy Dramas on Blu-ray"},"40381":{"$size":1,"size":1,"name":"Gritty Suspenseful Military Action & Adventure"},"40383":{"$size":1,"size":1,"name":"Dark Suspenseful War Movies"},"40385":{"$size":1,"size":1,"name":"Goofy Cult Stoner Movies"},"40387":{"$size":1,"size":1,"name":"Gritty Suspenseful Drug Movies"},"40389":{"$size":1,"size":1,"name":"Imaginative Suspenseful Alien Sci-Fi on Blu-ray"},"40390":{"$size":1,"size":1,"name":"Dark Independent Forbidden-Love Movies"},"40391":{"$size":1,"size":1,"name":"Imaginative Suspenseful Movies on Blu-ray"},"40392":{"$size":1,"size":1,"name":"Heartfelt Australian Movies"},"40394":{"$size":1,"size":1,"name":"Sentimental British Independent Movies"},"40398":{"$size":1,"size":1,"name":"Indian Crime Comedies"},"40400":{"$size":1,"size":1,"name":"Romantic Bollywood Crime Movies"},"40402":{"$size":1,"size":1,"name":"Comedies starring Mike Epps"},"40403":{"$size":1,"size":1,"name":"Cerebral Crime Thrillers on Blu-ray"},"40404":{"$size":1,"size":1,"name":"Emotional Independent Sports Movies"},"40407":{"$size":1,"size":1,"name":"Cult Evil Kid Horror Movies"},"40408":{"$size":1,"size":1,"name":"Cult Sports Movies"},"40412":{"$size":1,"size":1,"name":"Japanese Sports Movies"},"40415":{"$size":1,"size":1,"name":"Romantic Chinese Crime Movies"},"40417":{"$size":1,"size":1,"name":"Dark Suspenseful Sci-Fi Horror Movies"},"40418":{"$size":1,"size":1,"name":"Gritty Suspenseful Revenge Westerns"},"40419":{"$size":1,"size":1,"name":"Violent Suspenseful Action & Adventure from the 1980s"},"40421":{"$size":1,"size":1,"name":"Romantic Indian Crime Dramas"},"40422":{"$size":1,"size":1,"name":"Evil Kid Horror Films"},"40427":{"$size":1,"size":1,"name":"Critically-acclaimed Emotional Underdog Movies"},"40428":{"$size":1,"size":1,"name":"Understated Thrillers on Blu-ray"},"40430":{"$size":1,"size":1,"name":"Scandinavian Crime Thrillers"},"40434":{"$size":1,"size":1,"name":"Cerebral Sci-Fi Thrillers on Blu-ray"},"40435":{"$size":1,"size":1,"name":"Movies starring Rose Byrne"},"40437":{"$size":1,"size":1,"name":"Understated Crime Comedies"},"40439":{"$size":1,"size":1,"name":"Understated Crime Movies from the 1950s"},"40440":{"$size":1,"size":1,"name":"Gritty French-Language Crime Thrillers"},"40441":{"$size":1,"size":1,"name":"Emotional Independent Showbiz Dramas"},"40442":{"$size":1,"size":1,"name":"Violent French-Language Crime Thrillers"},"40443":{"$size":1,"size":1,"name":"Witty Spy Action & Adventure"},"40444":{"$size":1,"size":1,"name":"Spy Thrillers from the 1960s"},"40445":{"$size":1,"size":1,"name":"Stoner Comedies on Blu-ray"},"40450":{"$size":1,"size":1,"name":"Visually-striking Sci-Fi Horror Movies on Blu-ray"},"40451":{"$size":1,"size":1,"name":"Exciting Spy Movies from the 1980s"},"40452":{"$size":1,"size":1,"name":"Quirky Romantic Independent Comedies on Blu-ray"},"40453":{"$size":1,"size":1,"name":"Cerebral Biographical Dramas on Blu-ray"},"40455":{"$size":1,"size":1,"name":"Visually-striking British Movies from the 1970s"},"40458":{"$size":1,"size":1,"name":"Emotional Drug Dramas based on real life"},"40459":{"$size":1,"size":1,"name":"Gritty Spanish-Language Crime Movies"},"40460":{"$size":1,"size":1,"name":"Witty British Movies based on real life"},"40461":{"$size":1,"size":1,"name":"Bollywood Crime Dramas"},"40464":{"$size":1,"size":1,"name":"Sentimental Foreign Movies from the 1970s"},"40466":{"$size":1,"size":1,"name":"Suspenseful Conspiracy Movies based on bestsellers"},"40467":{"$size":1,"size":1,"name":"Emotional Reality TV"},"40468":{"$size":1,"size":1,"name":"Foreign Evil Kid Horror Movies"},"40470":{"$size":1,"size":1,"name":"Gritty Suspenseful Chase Movies"},"40471":{"$size":1,"size":1,"name":"Witty TV Sci-Fi & Fantasy Suspense"},"40474":{"$size":1,"size":1,"name":"Evil Kid Movies from the 1970s"},"40476":{"$size":1,"size":1,"name":"Gory Evil Kid Horror Movies"},"40480":{"$size":1,"size":1,"name":"Critically-acclaimed Imaginative Suspenseful Movies"},"40481":{"$size":1,"size":1,"name":"French-Language Spy Movies"},"40482":{"$size":1,"size":1,"name":"Visually-striking French-Language Crime Thrillers"},"40489":{"$size":1,"size":1,"name":"Crime Reality TV"},"40490":{"$size":1,"size":1,"name":"Witty Suspenseful Movies on Blu-ray"},"40494":{"$size":1,"size":1,"name":"Understated Biographical Crime Movies"},"40496":{"$size":1,"size":1,"name":"Raunchy Sports Movies on Blu-ray"},"40500":{"$size":1,"size":1,"name":"Imaginative Suspenseful Sci-Fi Adventure on Blu-ray"},"40501":{"$size":1,"size":1,"name":"Evil Kid Horror Movies from the 1970s"},"40506":{"$size":1,"size":1,"name":"British Independent Father-Son Relationship Dramas"},"40508":{"$size":1,"size":1,"name":"Witty 20th Century Period Pieces based on real life"},"40516":{"$size":1,"size":1,"name":"Gritty Suspenseful Independent Movies on Blu-ray"},"40517":{"$size":1,"size":1,"name":"Movies starring Ziyi Zhang"},"40519":{"$size":1,"size":1,"name":"Imaginative TV Cartoons"},"40523":{"$size":1,"size":1,"name":"Violent Evil Kid Movies"},"40524":{"$size":1,"size":1,"name":"Visually-striking Imaginative Revenge Movies"},"40525":{"$size":1,"size":1,"name":"Raunchy Sports Late Night Comedies"},"40527":{"$size":1,"size":1,"name":"Romantic Foreign Crime Comedies"},"40529":{"$size":1,"size":1,"name":"Violent Suspenseful War Movies"},"40531":{"$size":1,"size":1,"name":"Violent Suspenseful Rogue-Cop Action & Adventure"},"40536":{"$size":1,"size":1,"name":"Exciting Sports Reality TV"},"40538":{"$size":1,"size":1,"name":"Raunchy Cult Stoner Films"},"40540":{"$size":1,"size":1,"name":"Witty Suspenseful TV Shows from the 1960s"},"40544":{"$size":1,"size":1,"name":"Inspiring Foreign Sports Movies"},"40545":{"$size":1,"size":1,"name":"Dysfunctional-Family Movies based on bestsellers"},"40546":{"$size":1,"size":1,"name":"Gritty Movies starring Cuba Gooding Jr."},"40547":{"$size":1,"size":1,"name":"Understated French-Language Crime Dramas"},"40548":{"$size":1,"size":1,"name":"Visually-striking Military Dramas on Blu-ray"},"40549":{"$size":1,"size":1,"name":"Dark Australian Independent Dramas"},"40552":{"$size":1,"size":1,"name":"Steamy Heist Movies"},"40556":{"$size":1,"size":1,"name":"Feel-good Biographical Showbiz Documentaries"},"40559":{"$size":1,"size":1,"name":"Goofy Spy Comedies from the 1960s"},"40560":{"$size":1,"size":1,"name":"Violent Foreign Crime Movies from the 1980s"},"40561":{"$size":1,"size":1,"name":"Romantic Spanish-Language Crime Dramas"},"40562":{"$size":1,"size":1,"name":"Violent Suspenseful Spy Movies on Blu-ray"},"40563":{"$size":1,"size":1,"name":"Emotional Mother-Son Relationship Movies on Blu-ray"},"40564":{"$size":1,"size":1,"name":"Feel-good Biographical Sports Dramas"},"40566":{"$size":1,"size":1,"name":"Foreign Crime Dramas on Blu-ray"},"40567":{"$size":1,"size":1,"name":"Imaginative Suspenseful Sci-Fi Adventure"},"40569":{"$size":1,"size":1,"name":"Evil Kid Thrillers"},"40574":{"$size":1,"size":1,"name":"Violent Suspenseful Action Sci-Fi & Fantasy on Blu-ray"},"40576":{"$size":1,"size":1,"name":"Suspenseful Space-Travel TV Shows from the 1960s"},"40577":{"$size":1,"size":1,"name":"Gory Foreign Crime Action & Adventure"},"40579":{"$size":1,"size":1,"name":"Evil Kid Satanic Stories"},"40580":{"$size":1,"size":1,"name":"Raunchy Late Night Stoner Comedies"},"40581":{"$size":1,"size":1,"name":"Mad-Scientist Sci-Fi & Fantasy on Blu-ray"},"40582":{"$size":1,"size":1,"name":"Dark Independent Prison Dramas"},"40583":{"$size":1,"size":1,"name":"Dark Suspenseful Sci-Fi & Fantasy from the 1980s"},"40586":{"$size":1,"size":1,"name":"British Crime Movies based on classic literature"},"40593":{"$size":1,"size":1,"name":"Goofy Cult Stoner Comedies"},"40594":{"$size":1,"size":1,"name":"Visually-striking Crime Sci-Fi Thrillers"},"40596":{"$size":1,"size":1,"name":"Exciting Military 20th Century Period Pieces"},"40597":{"$size":1,"size":1,"name":"Scary Evil Kid Films"},"40598":{"$size":1,"size":1,"name":"Scandinavian Father-Son Relationship Dramas"},"40601":{"$size":1,"size":1,"name":"Stoner Movies on Blu-ray"},"40604":{"$size":1,"size":1,"name":"Cult Evil Kid Movies"},"40608":{"$size":1,"size":1,"name":"Scary Suspenseful Wilderness-survival Movies"},"40614":{"$size":1,"size":1,"name":"Gritty Foreign Crime Movies based on real life"},"40615":{"$size":1,"size":1,"name":"Gritty Crime Westerns based on real life"},"40617":{"$size":1,"size":1,"name":"Dark Suspenseful Movies based on bestsellers"},"40618":{"$size":1,"size":1,"name":"Visually-striking Understated Movies on Blu-ray"},"40622":{"$size":1,"size":1,"name":"Understated Suspenseful Political Movies"},"40624":{"$size":1,"size":1,"name":"Witty Spy Comedies"},"40627":{"$size":1,"size":1,"name":"Animation directed by Bill Melendez"},"40632":{"$size":1,"size":1,"name":"Inspiring Biographical Medical Movies"},"40634":{"$size":1,"size":1,"name":"Suspenseful Space-Travel TV Shows from the 1980s"},"40635":{"$size":1,"size":1,"name":"Visually-striking Dark Ghost-story Movies"},"40637":{"$size":1,"size":1,"name":"Evil Kid Films"},"40639":{"$size":1,"size":1,"name":"Gritty Suspenseful Rogue-Cop Action & Adventure"},"40640":{"$size":1,"size":1,"name":"Cult Stoner Late Night Comedies"},"40643":{"$size":1,"size":1,"name":"Movies starring Kang-ho Song"},"40645":{"$size":1,"size":1,"name":"Emotional Science & Nature Documentaries"},"40646":{"$size":1,"size":1,"name":"Critically-acclaimed Emotional Father-Daughter Relationship Movies"},"40647":{"$size":1,"size":1,"name":"Cerebral Suspenseful French-Language Movies"},"40649":{"$size":1,"size":1,"name":"Goofy Sports Movies for ages 8 to 10"},"40650":{"$size":1,"size":1,"name":"Romantic Reality TV"},"40651":{"$size":1,"size":1,"name":"Dark Evil Kid Movies"},"40653":{"$size":1,"size":1,"name":"Goofy TV Sketch Comedies from the 1970s"},"40655":{"$size":1,"size":1,"name":"Witty Suspenseful TV Shows from the 1980s"},"40659":{"$size":1,"size":1,"name":"Violent Crime Action & Adventure from the 1960s"},"40660":{"$size":1,"size":1,"name":"Critically-acclaimed French-Language Crime Thrillers"},"40661":{"$size":1,"size":1,"name":"Spy Dramas from the 1980s"},"40664":{"$size":1,"size":1,"name":"Evil Kid Suspense Films"},"40665":{"$size":1,"size":1,"name":"Workplace Late Night Comedies"},"40666":{"$size":1,"size":1,"name":"Gory Thrillers based on real life"},"40667":{"$size":1,"size":1,"name":"Controversial Foreign Dramas"},"40669":{"$size":1,"size":1,"name":"Secret-society Movies on Blu-ray"},"40670":{"$size":1,"size":1,"name":"Inspiring Sports Social & Cultural Documentaries"},"40671":{"$size":1,"size":1,"name":"Chinese Spy Movies"},"40676":{"$size":1,"size":1,"name":"Witty Foreign Crime Comedies"},"40680":{"$size":1,"size":1,"name":"Critically-acclaimed Understated Scandinavian Dramas"},"40682":{"$size":1,"size":1,"name":"Imaginative Suspenseful Space-Travel Movies"},"40685":{"$size":1,"size":1,"name":"Violent Suspenseful Drug Movies"},"40686":{"$size":1,"size":1,"name":"British Sci-Fi & Fantasy from the 1960s"},"40689":{"$size":1,"size":1,"name":"Visually-striking Imaginative Fight-the-System Movies"},"40692":{"$size":1,"size":1,"name":"Imaginative Suspenseful Movies from the 1980s"},"40693":{"$size":1,"size":1,"name":"Dark Father-Son Relationship Social Issue Dramas"},"40695":{"$size":1,"size":1,"name":"Imaginative Suspenseful Alien Sci-Fi"},"40699":{"$size":1,"size":1,"name":"Emotional Suspenseful Movies on Blu-ray"},"40700":{"$size":1,"size":1,"name":"Gory Sports Movies"},"40701":{"$size":1,"size":1,"name":"Goofy Baseball Comedies"},"40702":{"$size":1,"size":1,"name":"Dark Suspenseful Action Sci-Fi & Fantasy on Blu-ray"},"40705":{"$size":1,"size":1,"name":"Gory Evil Kid Movies"},"40706":{"$size":1,"size":1,"name":"Witty TV Comedies on Blu-ray"},"40710":{"$size":1,"size":1,"name":"Emotional Independent Showbiz Movies"},"40714":{"$size":1,"size":1,"name":"Critically-acclaimed Crime Art House Movies"},"40715":{"$size":1,"size":1,"name":"Understated TV Shows on Blu-ray"},"40718":{"$size":1,"size":1,"name":"Understated Crime Documentaries"},"40719":{"$size":1,"size":1,"name":"Italian Crime Comedies"},"40725":{"$size":1,"size":1,"name":"Scary Suspenseful Mad-Scientist Sci-Fi & Fantasy"},"40726":{"$size":1,"size":1,"name":"Movies directed by Bill Melendez"},"40729":{"$size":1,"size":1,"name":"Dark Dysfunctional-Family Thrillers"},"40731":{"$size":1,"size":1,"name":"Critically-acclaimed Witty Crime Movies on Blu-ray"},"40734":{"$size":1,"size":1,"name":"Violent Suspenseful Martial Arts Movies"},"40736":{"$size":1,"size":1,"name":"Film Noir based on classic literature"},"40737":{"$size":1,"size":1,"name":"Spy Mysteries from the 1940s"},"40738":{"$size":1,"size":1,"name":"Critically-acclaimed Witty Dramas based on real life"},"40739":{"$size":1,"size":1,"name":"Critically-acclaimed Violent Foreign Crime Movies"},"40740":{"$size":1,"size":1,"name":"Sentimental British 20th Century Period Pieces"},"40741":{"$size":1,"size":1,"name":"Imaginative Suspenseful Sci-Fi & Fantasy on Blu-ray"},"40742":{"$size":1,"size":1,"name":"Gritty Suspenseful Action & Adventure from the 1960s"},"40745":{"$size":1,"size":1,"name":"Imaginative TV Suspense Programmes"},"40750":{"$size":1,"size":1,"name":"Gritty Independent Sports Dramas"},"40753":{"$size":1,"size":1,"name":"Evil Kid Movies on Blu-ray"},"40754":{"$size":1,"size":1,"name":"Exciting Sports Documentaries"},"40755":{"$size":1,"size":1,"name":"Emotional Dysfunctional-Family Movies on Blu-ray"},"40756":{"$size":1,"size":1,"name":"Violent Suspenseful Foreign Action & Adventure"},"40758":{"$size":1,"size":1,"name":"Argentinian Crime Dramas"},"40761":{"$size":1,"size":1,"name":"Foreign Crime Steamy Romance"},"40765":{"$size":1,"size":1,"name":"Witty TV Sci-Fi & Fantasy from the 1980s"},"40768":{"$size":1,"size":1,"name":"Sports Movies for ages 2 to 4"},"40771":{"$size":1,"size":1,"name":"Understated Suspenseful British Movies"},"40772":{"$size":1,"size":1,"name":"Comedies based on bestsellers"},"40774":{"$size":1,"size":1,"name":"Witty Suspenseful Movies from the 1970s"},"40778":{"$size":1,"size":1,"name":"Conspiracy Sci-Fi Thrillers on Blu-ray"},"40779":{"$size":1,"size":1,"name":"Biographical Documentaries about Food"},"40780":{"$size":1,"size":1,"name":"Witty Crime Comedies on Blu-ray"},"40781":{"$size":1,"size":1,"name":"Critically-acclaimed Feel-good Animation on Blu-ray"},"40785":{"$size":1,"size":1,"name":"Quirky Crime Comedies on Blu-ray"},"40786":{"$size":1,"size":1,"name":"Gritty Suspenseful French-Language Movies"},"40792":{"$size":1,"size":1,"name":"Understated Suspenseful Movies from the 1950s"},"40793":{"$size":1,"size":1,"name":"Foreign Evil Kid Movies"},"40798":{"$size":1,"size":1,"name":"Visually-striking Gritty Suspenseful Movies on Blu-ray"},"40799":{"$size":1,"size":1,"name":"Foreign Spy Movies from the 1960s"},"40800":{"$size":1,"size":1,"name":"Mexican Crime Comedies"},"40804":{"$size":1,"size":1,"name":"Controversial LGBT Dramas"},"40805":{"$size":1,"size":1,"name":"Gritty Sports Movies from the 1980s"},"40806":{"$size":1,"size":1,"name":"Critically-acclaimed Sports Comedies"},"40808":{"$size":1,"size":1,"name":"Children & Family Movies directed by Bill Melendez"},"40809":{"$size":1,"size":1,"name":"British Crime Movies from the 1950s"},"40813":{"$size":1,"size":1,"name":"Scary British Serial-Killer Movies"},"40815":{"$size":1,"size":1,"name":"Raunchy Cult Stoner Comedies"},"40816":{"$size":1,"size":1,"name":"Violent Brazilian Movies"},"40817":{"$size":1,"size":1,"name":"Cerebral Suspenseful Movies from the 1980s"},"40819":{"$size":1,"size":1,"name":"Imaginative Suspenseful Space-Travel Movies on Blu-ray"},"40822":{"$size":1,"size":1,"name":"Visually-striking Foreign Crime Movies from the 1960s"},"40823":{"$size":1,"size":1,"name":"Sports Social Issue Dramas"},"40824":{"$size":1,"size":1,"name":"Critically-acclaimed Witty Dramas on Blu-ray"},"40829":{"$size":1,"size":1,"name":"Raunchy Cult Stoner Late Night Comedies"},"40834":{"$size":1,"size":1,"name":"Emotional Teen Coming-of-age Dramas"},"40835":{"$size":1,"size":1,"name":"Dramas starring Shintar\u00F4 Katsu"},"40838":{"$size":1,"size":1,"name":"Emotional Australian Independent Movies"},"40841":{"$size":1,"size":1,"name":"Emotional Russian Dramas"},"40843":{"$size":1,"size":1,"name":"Emotional Wedding Dramas"},"40846":{"$size":1,"size":1,"name":"Sentimental Australian Movies"},"40850":{"$size":1,"size":1,"name":"Visually-striking Bounty-Hunter Movies"},"40851":{"$size":1,"size":1,"name":"Critically-acclaimed Understated Immigrant-Life Dramas"},"40852":{"$size":1,"size":1,"name":"Visually-striking British Comedies"},"40854":{"$size":1,"size":1,"name":"Critically-acclaimed Independent Comedies on Blu-ray"},"40855":{"$size":1,"size":1,"name":"Gritty Spy Movies on Blu-ray"},"40861":{"$size":1,"size":1,"name":"Suspenseful Conspiracy Action & Adventure on Blu-ray"},"40862":{"$size":1,"size":1,"name":"Imaginative Post-Apocalypse Action Sci-Fi & Fantasy"},"40863":{"$size":1,"size":1,"name":"Critically-acclaimed Dark Foreign Documentaries"},"40872":{"$size":1,"size":1,"name":"Critically-acclaimed Raunchy Movies on Blu-ray"},"40873":{"$size":1,"size":1,"name":"Dark Drug Movies on Blu-ray"},"40874":{"$size":1,"size":1,"name":"Independent Father-Daughter Relationship Tearjerkers"},"40875":{"$size":1,"size":1,"name":"Whistleblower Movies on Blu-ray"},"40876":{"$size":1,"size":1,"name":"Biographical Mother-Daughter Relationship Documentaries"},"40877":{"$size":1,"size":1,"name":"Emotional Foreign Dramas on Blu-ray"},"40879":{"$size":1,"size":1,"name":"Foreign Fight-the-System Thrillers"},"40880":{"$size":1,"size":1,"name":"Critically-acclaimed Gritty Immigrant-Life Movies"},"40881":{"$size":1,"size":1,"name":"Dark Movies starring Mickey Rourke"},"40882":{"$size":1,"size":1,"name":"Dramas directed by John Kent Harrison"},"40884":{"$size":1,"size":1,"name":"Imaginative Comedies on Blu-ray"},"40886":{"$size":1,"size":1,"name":"Cerebral British Conspiracy Movies"},"40887":{"$size":1,"size":1,"name":"Critically-acclaimed French-Language Documentaries"},"40890":{"$size":1,"size":1,"name":"Gritty British Films based on contemporary literature"},"40892":{"$size":1,"size":1,"name":"Emotional British Movies on Blu-ray"},"40893":{"$size":1,"size":1,"name":"Gory Wilderness-survival Monster Movies"},"40894":{"$size":1,"size":1,"name":"Understated Prison Dramas"},"40900":{"$size":1,"size":1,"name":"Showbiz 20th Century Period Pieces on Blu-ray"},"40904":{"$size":1,"size":1,"name":"Heartfelt Father-Son Relationship Movies on Blu-ray"},"40906":{"$size":1,"size":1,"name":"Dark Suspenseful Movies on Blu-ray from the 1980s"},"40911":{"$size":1,"size":1,"name":"Dramas starring Tatsuya Nakadai"},"40915":{"$size":1,"size":1,"name":"Dark Sci-Fi Dramas from the 1980s"},"40917":{"$size":1,"size":1,"name":"Scary Scandinavian Movies"},"40918":{"$size":1,"size":1,"name":"Dramas directed by Manoel de Oliveira"},"40926":{"$size":1,"size":1,"name":"British Football Films"},"40927":{"$size":1,"size":1,"name":"French-Language Crime Movies on Blu-ray"},"40929":{"$size":1,"size":1,"name":"Revenge Late Night Comedies"},"40935":{"$size":1,"size":1,"name":"Heartfelt British Independent Dramas"},"40937":{"$size":1,"size":1,"name":"Dark Sci-Fi & Fantasy on Blu-ray from the 1980s"},"40944":{"$size":1,"size":1,"name":"Critically-acclaimed Inspiring Sports Documentaries"},"40946":{"$size":1,"size":1,"name":"German-Language Movies on Blu-ray"},"40947":{"$size":1,"size":1,"name":"Australian Showbiz Movies"},"40948":{"$size":1,"size":1,"name":"Visually-striking Psychological Sci-Fi & Fantasy"},"40949":{"$size":1,"size":1,"name":"Critically-acclaimed Japanese Dramas from the 1950s"},"40952":{"$size":1,"size":1,"name":"Emotional Sports Documentaries"},"40956":{"$size":1,"size":1,"name":"Visually-striking Violent British Movies"}}},"error":{"innerErrors":[{"message":"OnError while emitting onNext value: com.netflix.api.service.video.APIGenreImpl.class","pql":["genres",[39962],"name"]},{"message":"OnError while emitting onNext value: com.netflix.api.service.video.APIGenreImpl.class","pql":["genres",[39963],"name"]},{"message":"OnError while emitting onNext value: com.netflix.api.service.video.APIGenreImpl.class","pql":["genres",[39965],"name"]},{"message":"OnError while emitting onNext value: com.netflix.api.service.video.APIGenreImpl.class","pql":["genres",[39966],"name"]},{"message":"OnError while emitting onNext value: com.netflix.api.service.video.APIGenreImpl.class","pql":["genres",[39967],"name"]},{"message":"OnError while emitting onNext value: com.netflix.api.service.video.APIGenreImpl.class","pql":["genres",[39968],"name"]},{"message":"OnError while emitting onNext value: com.netflix.api.service.video.APIGenreImpl.class","pql":["genres",[39970],"name"]},{"message":"OnError while emitting onNext value: com.netflix.api.service.video.APIGenreImpl.class","pql":["genres",[39971],"name"]},{"message":"OnError while emitting onNext value: com.netflix.api.service.video.APIGenreImpl.class","pql":["genres",[39972],"name"]},{"message":"OnError while emitting onNext value: com.netflix.api.service.video.APIGenreImpl.class","pql":["genres",[39973],"name"]},{"message":"OnError while emitting onNext value: com.netflix.api.service.video.APIGenreImpl.class","pql":["genres",[39974],"name"]},{"message":"OnError while emitting onNext value: com.netflix.api.service.video.APIGenreImpl.class","pql":["genres",[39976],"name"]},{"message":"OnError while emitting onNext value: com.netflix.api.service.video.APIGenreImpl.class","pql":["genres",[39979],"name"]},{"message":"OnError while emitting onNext value: com.netflix.api.service.video.APIGenreImpl.class","pql":["genres",[39980],"name"]},{"message":"OnError while emitting onNext value: com.netflix.api.service.video.APIGenreImpl.class","pql":["genres",[39981],"name"]},{"message":"OnError while emitting onNext value: com.netflix.api.service.video.APIGenreImpl.class","pql":["genres",[39983],"name"]},{"message":"OnError while emitting onNext value: com.netflix.api.service.video.APIGenreImpl.class","pql":["genres",[39984],"name"]},{"message":"OnError while emitting onNext value: com.netflix.api.service.video.APIGenreImpl.class","pql":["genres",[39985],"name"]},{"message":"OnError while emitting onNext value: com.netflix.api.service.video.APIGenreImpl.class","pql":["genres",[39986],"name"]},{"message":"OnError while emitting onNext value: com.netflix.api.service.video.APIGenreImpl.class","pql":["genres",[39987],"name"]},{"message":"OnError while emitting onNext value: com.netflix.api.service.video.APIGenreImpl.class","pql":["genres",[39990],"name"]},{"message":null,"pql":["genres",[39993],"name"]},{"message":null,"pql":["genres",[39994],"name"]},{"message":null,"pql":["genres",[39995],"name"]},{"message":null,"pql":["genres",[39996],"name"]},{"message":null,"pql":["genres",[39997],"name"]},{"message":null,"pql":["genres",[40000],"name"]},{"message":null,"pql":["genres",[40002],"name"]},{"message":null,"pql":["genres",[40003],"name"]},{"message":null,"pql":["genres",[40005],"name"]},{"message":null,"pql":["genres",[40009],"name"]},{"message":null,"pql":["genres",[40010],"name"]},{"message":null,"pql":["genres",[40011],"name"]},{"message":null,"pql":["genres",[40012],"name"]},{"message":null,"pql":["genres",[40013],"name"]},{"message":null,"pql":["genres",[40015],"name"]},{"message":null,"pql":["genres",[40016],"name"]},{"message":null,"pql":["genres",[40018],"name"]},{"message":null,"pql":["genres",[40019],"name"]},{"message":null,"pql":["genres",[40022],"name"]},{"message":null,"pql":["genres",[40025],"name"]},{"message":null,"pql":["genres",[40027],"name"]},{"message":null,"pql":["genres",[40029],"name"]},{"message":null,"pql":["genres",[40030],"name"]},{"message":null,"pql":["genres",[40031],"name"]},{"message":null,"pql":["genres",[40032],"name"]},{"message":null,"pql":["genres",[40035],"name"]},{"message":null,"pql":["genres",[40036],"name"]},{"message":null,"pql":["genres",[40037],"name"]},{"message":null,"pql":["genres",[40038],"name"]},{"message":null,"pql":["genres",[40039],"name"]},{"message":null,"pql":["genres",[40040],"name"]},{"message":null,"pql":["genres",[40041],"name"]},{"message":null,"pql":["genres",[40043],"name"]},{"message":null,"pql":["genres",[40044],"name"]},{"message":null,"pql":["genres",[40045],"name"]},{"message":null,"pql":["genres",[40049],"name"]},{"message":null,"pql":["genres",[40050],"name"]},{"message":null,"pql":["genres",[40053],"name"]},{"message":null,"pql":["genres",[40055],"name"]},{"message":null,"pql":["genres",[40056],"name"]},{"message":null,"pql":["genres",[40060],"name"]},{"message":null,"pql":["genres",[40061],"name"]},{"message":null,"pql":["genres",[40062],"name"]},{"message":null,"pql":["genres",[40063],"name"]},{"message":null,"pql":["genres",[40064],"name"]},{"message":null,"pql":["genres",[40066],"name"]},{"message":null,"pql":["genres",[40069],"name"]},{"message":null,"pql":["genres",[40071],"name"]},{"message":null,"pql":["genres",[40074],"name"]},{"message":null,"pql":["genres",[40076],"name"]},{"message":null,"pql":["genres",[40077],"name"]},{"message":null,"pql":["genres",[40079],"name"]},{"message":null,"pql":["genres",[40082],"name"]},{"message":null,"pql":["genres",[40086],"name"]},{"message":null,"pql":["genres",[40087],"name"]},{"message":null,"pql":["genres",[40092],"name"]},{"message":null,"pql":["genres",[40093],"name"]},{"message":null,"pql":["genres",[40097],"name"]},{"message":null,"pql":["genres",[40099],"name"]},{"message":null,"pql":["genres",[40101],"name"]},{"message":null,"pql":["genres",[40102],"name"]},{"message":null,"pql":["genres",[40105],"name"]},{"message":null,"pql":["genres",[40106],"name"]},{"message":null,"pql":["genres",[40107],"name"]},{"message":null,"pql":["genres",[40108],"name"]},{"message":null,"pql":["genres",[40110],"name"]},{"message":null,"pql":["genres",[40111],"name"]},{"message":null,"pql":["genres",[40112],"name"]},{"message":null,"pql":["genres",[40115],"name"]},{"message":null,"pql":["genres",[40116],"name"]},{"message":null,"pql":["genres",[40117],"name"]},{"message":null,"pql":["genres",[40118],"name"]},{"message":null,"pql":["genres",[40121],"name"]},{"message":null,"pql":["genres",[40122],"name"]},{"message":null,"pql":["genres",[40123],"name"]},{"message":null,"pql":["genres",[40125],"name"]},{"message":null,"pql":["genres",[40126],"name"]},{"message":null,"pql":["genres",[40129],"name"]},{"message":null,"pql":["genres",[40133],"name"]},{"message":null,"pql":["genres",[40134],"name"]},{"message":null,"pql":["genres",[40135],"name"]},{"message":null,"pql":["genres",[40139],"name"]},{"message":null,"pql":["genres",[40140],"name"]},{"message":null,"pql":["genres",[40141],"name"]},{"message":null,"pql":["genres",[40142],"name"]},{"message":null,"pql":["genres",[40146],"name"]},{"message":null,"pql":["genres",[40148],"name"]},{"message":null,"pql":["genres",[40149],"name"]},{"message":null,"pql":["genres",[40150],"name"]},{"message":null,"pql":["genres",[40151],"name"]},{"message":null,"pql":["genres",[40152],"name"]},{"message":null,"pql":["genres",[40157],"name"]},{"message":null,"pql":["genres",[40159],"name"]},{"message":null,"pql":["genres",[40160],"name"]},{"message":null,"pql":["genres",[40165],"name"]},{"message":null,"pql":["genres",[40167],"name"]},{"message":null,"pql":["genres",[40171],"name"]},{"message":null,"pql":["genres",[40172],"name"]},{"message":null,"pql":["genres",[40174],"name"]},{"message":null,"pql":["genres",[40175],"name"]},{"message":null,"pql":["genres",[40178],"name"]},{"message":null,"pql":["genres",[40179],"name"]},{"message":null,"pql":["genres",[40181],"name"]},{"message":null,"pql":["genres",[40182],"name"]},{"message":null,"pql":["genres",[40185],"name"]},{"message":null,"pql":["genres",[40186],"name"]},{"message":null,"pql":["genres",[40188],"name"]},{"message":null,"pql":["genres",[40190],"name"]},{"message":null,"pql":["genres",[40191],"name"]},{"message":null,"pql":["genres",[40194],"name"]},{"message":null,"pql":["genres",[40196],"name"]},{"message":null,"pql":["genres",[40197],"name"]},{"message":null,"pql":["genres",[40201],"name"]},{"message":null,"pql":["genres",[40202],"name"]},{"message":null,"pql":["genres",[40205],"name"]},{"message":null,"pql":["genres",[40206],"name"]},{"message":null,"pql":["genres",[40207],"name"]},{"message":null,"pql":["genres",[40208],"name"]},{"message":null,"pql":["genres",[40209],"name"]},{"message":null,"pql":["genres",[40212],"name"]},{"message":null,"pql":["genres",[40218],"name"]},{"message":null,"pql":["genres",[40221],"name"]},{"message":null,"pql":["genres",[40225],"name"]},{"message":null,"pql":["genres",[40226],"name"]},{"message":null,"pql":["genres",[40227],"name"]},{"message":null,"pql":["genres",[40228],"name"]},{"message":null,"pql":["genres",[40231],"name"]},{"message":null,"pql":["genres",[40237],"name"]},{"message":null,"pql":["genres",[40238],"name"]},{"message":null,"pql":["genres",[40239],"name"]},{"message":null,"pql":["genres",[40241],"name"]},{"message":null,"pql":["genres",[40242],"name"]},{"message":null,"pql":["genres",[40244],"name"]},{"message":null,"pql":["genres",[40245],"name"]},{"message":null,"pql":["genres",[40246],"name"]},{"message":null,"pql":["genres",[40248],"name"]},{"message":null,"pql":["genres",[40249],"name"]},{"message":null,"pql":["genres",[40250],"name"]},{"message":null,"pql":["genres",[40256],"name"]},{"message":null,"pql":["genres",[40257],"name"]},{"message":null,"pql":["genres",[40258],"name"]},{"message":null,"pql":["genres",[40260],"name"]},{"message":null,"pql":["genres",[40265],"name"]},{"message":null,"pql":["genres",[40269],"name"]},{"message":null,"pql":["genres",[40273],"name"]},{"message":null,"pql":["genres",[40274],"name"]},{"message":null,"pql":["genres",[40275],"name"]},{"message":null,"pql":["genres",[40279],"name"]},{"message":null,"pql":["genres",[40280],"name"]},{"message":null,"pql":["genres",[40281],"name"]},{"message":null,"pql":["genres",[40282],"name"]},{"message":null,"pql":["genres",[40283],"name"]},{"message":null,"pql":["genres",[40286],"name"]},{"message":null,"pql":["genres",[40289],"name"]},{"message":null,"pql":["genres",[40290],"name"]},{"message":null,"pql":["genres",[40291],"name"]},{"message":null,"pql":["genres",[40292],"name"]},{"message":null,"pql":["genres",[40293],"name"]},{"message":null,"pql":["genres",[40296],"name"]},{"message":null,"pql":["genres",[40299],"name"]},{"message":null,"pql":["genres",[40303],"name"]},{"message":null,"pql":["genres",[40305],"name"]},{"message":null,"pql":["genres",[40309],"name"]},{"message":null,"pql":["genres",[40310],"name"]},{"message":null,"pql":["genres",[40312],"name"]},{"message":null,"pql":["genres",[40313],"name"]},{"message":null,"pql":["genres",[40316],"name"]},{"message":null,"pql":["genres",[40318],"name"]},{"message":null,"pql":["genres",[40321],"name"]},{"message":null,"pql":["genres",[40323],"name"]},{"message":null,"pql":["genres",[40324],"name"]},{"message":null,"pql":["genres",[40326],"name"]},{"message":null,"pql":["genres",[40327],"name"]},{"message":null,"pql":["genres",[40330],"name"]},{"message":null,"pql":["genres",[40331],"name"]},{"message":null,"pql":["genres",[40332],"name"]},{"message":null,"pql":["genres",[40334],"name"]},{"message":null,"pql":["genres",[40344],"name"]},{"message":null,"pql":["genres",[40345],"name"]},{"message":null,"pql":["genres",[40348],"name"]},{"message":null,"pql":["genres",[40353],"name"]},{"message":null,"pql":["genres",[40357],"name"]},{"message":null,"pql":["genres",[40358],"name"]},{"message":null,"pql":["genres",[40359],"name"]},{"message":null,"pql":["genres",[40360],"name"]},{"message":null,"pql":["genres",[40361],"name"]},{"message":null,"pql":["genres",[40362],"name"]},{"message":null,"pql":["genres",[40365],"name"]},{"message":null,"pql":["genres",[40368],"name"]},{"message":null,"pql":["genres",[40369],"name"]},{"message":null,"pql":["genres",[40373],"name"]},{"message":null,"pql":["genres",[40375],"name"]},{"message":null,"pql":["genres",[40376],"name"]},{"message":null,"pql":["genres",[40378],"name"]},{"message":null,"pql":["genres",[40379],"name"]},{"message":null,"pql":["genres",[40382],"name"]},{"message":null,"pql":["genres",[40384],"name"]},{"message":null,"pql":["genres",[40386],"name"]},{"message":null,"pql":["genres",[40388],"name"]},{"message":null,"pql":["genres",[40393],"name"]},{"message":null,"pql":["genres",[40395],"name"]},{"message":null,"pql":["genres",[40396],"name"]},{"message":null,"pql":["genres",[40397],"name"]},{"message":null,"pql":["genres",[40399],"name"]},{"message":null,"pql":["genres",[40401],"name"]},{"message":null,"pql":["genres",[40405],"name"]},{"message":null,"pql":["genres",[40406],"name"]},{"message":null,"pql":["genres",[40409],"name"]},{"message":null,"pql":["genres",[40410],"name"]},{"message":null,"pql":["genres",[40411],"name"]},{"message":null,"pql":["genres",[40413],"name"]},{"message":null,"pql":["genres",[40414],"name"]},{"message":null,"pql":["genres",[40416],"name"]},{"message":null,"pql":["genres",[40420],"name"]},{"message":null,"pql":["genres",[40423],"name"]},{"message":null,"pql":["genres",[40424],"name"]},{"message":null,"pql":["genres",[40425],"name"]},{"message":null,"pql":["genres",[40426],"name"]},{"message":null,"pql":["genres",[40429],"name"]},{"message":null,"pql":["genres",[40431],"name"]},{"message":null,"pql":["genres",[40432],"name"]},{"message":null,"pql":["genres",[40433],"name"]},{"message":null,"pql":["genres",[40436],"name"]},{"message":null,"pql":["genres",[40438],"name"]},{"message":null,"pql":["genres",[40446],"name"]},{"message":null,"pql":["genres",[40447],"name"]},{"message":null,"pql":["genres",[40448],"name"]},{"message":null,"pql":["genres",[40449],"name"]},{"message":null,"pql":["genres",[40454],"name"]},{"message":null,"pql":["genres",[40456],"name"]},{"message":null,"pql":["genres",[40457],"name"]},{"message":null,"pql":["genres",[40462],"name"]},{"message":null,"pql":["genres",[40463],"name"]},{"message":null,"pql":["genres",[40465],"name"]},{"message":null,"pql":["genres",[40469],"name"]},{"message":null,"pql":["genres",[40472],"name"]},{"message":null,"pql":["genres",[40473],"name"]},{"message":null,"pql":["genres",[40475],"name"]},{"message":null,"pql":["genres",[40477],"name"]},{"message":null,"pql":["genres",[40478],"name"]},{"message":null,"pql":["genres",[40479],"name"]},{"message":null,"pql":["genres",[40483],"name"]},{"message":null,"pql":["genres",[40484],"name"]},{"message":null,"pql":["genres",[40485],"name"]},{"message":null,"pql":["genres",[40486],"name"]},{"message":null,"pql":["genres",[40487],"name"]},{"message":null,"pql":["genres",[40488],"name"]},{"message":null,"pql":["genres",[40491],"name"]},{"message":null,"pql":["genres",[40492],"name"]},{"message":null,"pql":["genres",[40493],"name"]},{"message":null,"pql":["genres",[40495],"name"]},{"message":null,"pql":["genres",[40497],"name"]},{"message":null,"pql":["genres",[40498],"name"]},{"message":null,"pql":["genres",[40499],"name"]},{"message":null,"pql":["genres",[40502],"name"]},{"message":null,"pql":["genres",[40503],"name"]},{"message":null,"pql":["genres",[40504],"name"]},{"message":null,"pql":["genres",[40505],"name"]},{"message":null,"pql":["genres",[40507],"name"]},{"message":null,"pql":["genres",[40509],"name"]},{"message":null,"pql":["genres",[40510],"name"]},{"message":null,"pql":["genres",[40511],"name"]},{"message":null,"pql":["genres",[40512],"name"]},{"message":null,"pql":["genres",[40513],"name"]},{"message":null,"pql":["genres",[40514],"name"]},{"message":null,"pql":["genres",[40515],"name"]},{"message":null,"pql":["genres",[40518],"name"]},{"message":null,"pql":["genres",[40520],"name"]},{"message":null,"pql":["genres",[40521],"name"]},{"message":null,"pql":["genres",[40522],"name"]},{"message":null,"pql":["genres",[40526],"name"]},{"message":null,"pql":["genres",[40528],"name"]},{"message":null,"pql":["genres",[40530],"name"]},{"message":null,"pql":["genres",[40532],"name"]},{"message":null,"pql":["genres",[40533],"name"]},{"message":null,"pql":["genres",[40534],"name"]},{"message":null,"pql":["genres",[40535],"name"]},{"message":null,"pql":["genres",[40537],"name"]},{"message":null,"pql":["genres",[40539],"name"]},{"message":null,"pql":["genres",[40541],"name"]},{"message":null,"pql":["genres",[40542],"name"]},{"message":null,"pql":["genres",[40543],"name"]},{"message":null,"pql":["genres",[40550],"name"]},{"message":null,"pql":["genres",[40551],"name"]},{"message":null,"pql":["genres",[40553],"name"]},{"message":null,"pql":["genres",[40554],"name"]},{"message":null,"pql":["genres",[40555],"name"]},{"message":null,"pql":["genres",[40557],"name"]},{"message":null,"pql":["genres",[40558],"name"]},{"message":null,"pql":["genres",[40565],"name"]},{"message":null,"pql":["genres",[40568],"name"]},{"message":null,"pql":["genres",[40570],"name"]},{"message":null,"pql":["genres",[40571],"name"]},{"message":null,"pql":["genres",[40572],"name"]},{"message":null,"pql":["genres",[40573],"name"]},{"message":null,"pql":["genres",[40575],"name"]},{"message":null,"pql":["genres",[40578],"name"]},{"message":null,"pql":["genres",[40584],"name"]},{"message":null,"pql":["genres",[40585],"name"]},{"message":null,"pql":["genres",[40587],"name"]},{"message":null,"pql":["genres",[40588],"name"]},{"message":null,"pql":["genres",[40589],"name"]},{"message":null,"pql":["genres",[40590],"name"]},{"message":null,"pql":["genres",[40591],"name"]},{"message":null,"pql":["genres",[40592],"name"]},{"message":null,"pql":["genres",[40595],"name"]},{"message":null,"pql":["genres",[40599],"name"]},{"message":null,"pql":["genres",[40600],"name"]},{"message":null,"pql":["genres",[40602],"name"]},{"message":null,"pql":["genres",[40603],"name"]},{"message":null,"pql":["genres",[40605],"name"]},{"message":null,"pql":["genres",[40606],"name"]},{"message":null,"pql":["genres",[40607],"name"]},{"message":null,"pql":["genres",[40609],"name"]},{"message":null,"pql":["genres",[40610],"name"]},{"message":null,"pql":["genres",[40611],"name"]},{"message":null,"pql":["genres",[40612],"name"]},{"message":null,"pql":["genres",[40613],"name"]},{"message":null,"pql":["genres",[40616],"name"]},{"message":null,"pql":["genres",[40619],"name"]},{"message":null,"pql":["genres",[40620],"name"]},{"message":null,"pql":["genres",[40621],"name"]},{"message":null,"pql":["genres",[40623],"name"]},{"message":null,"pql":["genres",[40625],"name"]},{"message":null,"pql":["genres",[40626],"name"]},{"message":null,"pql":["genres",[40628],"name"]},{"message":null,"pql":["genres",[40629],"name"]},{"message":null,"pql":["genres",[40630],"name"]},{"message":null,"pql":["genres",[40631],"name"]},{"message":null,"pql":["genres",[40633],"name"]},{"message":null,"pql":["genres",[40636],"name"]},{"message":null,"pql":["genres",[40638],"name"]},{"message":null,"pql":["genres",[40641],"name"]},{"message":null,"pql":["genres",[40642],"name"]},{"message":null,"pql":["genres",[40644],"name"]},{"message":null,"pql":["genres",[40648],"name"]},{"message":null,"pql":["genres",[40652],"name"]},{"message":null,"pql":["genres",[40654],"name"]},{"message":null,"pql":["genres",[40656],"name"]},{"message":null,"pql":["genres",[40657],"name"]},{"message":null,"pql":["genres",[40658],"name"]},{"message":null,"pql":["genres",[40662],"name"]},{"message":null,"pql":["genres",[40663],"name"]},{"message":null,"pql":["genres",[40668],"name"]},{"message":null,"pql":["genres",[40672],"name"]},{"message":null,"pql":["genres",[40673],"name"]},{"message":null,"pql":["genres",[40674],"name"]},{"message":null,"pql":["genres",[40675],"name"]},{"message":null,"pql":["genres",[40677],"name"]},{"message":null,"pql":["genres",[40678],"name"]},{"message":null,"pql":["genres",[40679],"name"]},{"message":null,"pql":["genres",[40681],"name"]},{"message":null,"pql":["genres",[40683],"name"]},{"message":null,"pql":["genres",[40684],"name"]},{"message":null,"pql":["genres",[40687],"name"]},{"message":null,"pql":["genres",[40688],"name"]},{"message":null,"pql":["genres",[40690],"name"]},{"message":null,"pql":["genres",[40691],"name"]},{"message":null,"pql":["genres",[40694],"name"]},{"message":null,"pql":["genres",[40696],"name"]},{"message":null,"pql":["genres",[40697],"name"]},{"message":null,"pql":["genres",[40698],"name"]},{"message":null,"pql":["genres",[40703],"name"]},{"message":null,"pql":["genres",[40704],"name"]},{"message":null,"pql":["genres",[40707],"name"]},{"message":null,"pql":["genres",[40708],"name"]},{"message":null,"pql":["genres",[40709],"name"]},{"message":null,"pql":["genres",[40711],"name"]},{"message":null,"pql":["genres",[40712],"name"]},{"message":null,"pql":["genres",[40713],"name"]},{"message":null,"pql":["genres",[40716],"name"]},{"message":null,"pql":["genres",[40717],"name"]},{"message":null,"pql":["genres",[40720],"name"]},{"message":null,"pql":["genres",[40721],"name"]},{"message":null,"pql":["genres",[40722],"name"]},{"message":null,"pql":["genres",[40723],"name"]},{"message":null,"pql":["genres",[40724],"name"]},{"message":null,"pql":["genres",[40727],"name"]},{"message":null,"pql":["genres",[40728],"name"]},{"message":null,"pql":["genres",[40730],"name"]},{"message":null,"pql":["genres",[40732],"name"]},{"message":null,"pql":["genres",[40733],"name"]},{"message":null,"pql":["genres",[40735],"name"]},{"message":null,"pql":["genres",[40743],"name"]},{"message":null,"pql":["genres",[40744],"name"]},{"message":null,"pql":["genres",[40746],"name"]},{"message":null,"pql":["genres",[40747],"name"]},{"message":null,"pql":["genres",[40748],"name"]},{"message":null,"pql":["genres",[40749],"name"]},{"message":null,"pql":["genres",[40751],"name"]},{"message":null,"pql":["genres",[40752],"name"]},{"message":null,"pql":["genres",[40757],"name"]},{"message":null,"pql":["genres",[40759],"name"]},{"message":null,"pql":["genres",[40760],"name"]},{"message":null,"pql":["genres",[40762],"name"]},{"message":null,"pql":["genres",[40763],"name"]},{"message":null,"pql":["genres",[40764],"name"]},{"message":null,"pql":["genres",[40766],"name"]},{"message":null,"pql":["genres",[40767],"name"]},{"message":null,"pql":["genres",[40769],"name"]},{"message":null,"pql":["genres",[40770],"name"]},{"message":null,"pql":["genres",[40773],"name"]},{"message":null,"pql":["genres",[40775],"name"]},{"message":null,"pql":["genres",[40776],"name"]},{"message":null,"pql":["genres",[40777],"name"]},{"message":null,"pql":["genres",[40782],"name"]},{"message":null,"pql":["genres",[40783],"name"]},{"message":null,"pql":["genres",[40784],"name"]},{"message":null,"pql":["genres",[40787],"name"]},{"message":null,"pql":["genres",[40788],"name"]},{"message":null,"pql":["genres",[40789],"name"]},{"message":null,"pql":["genres",[40790],"name"]},{"message":null,"pql":["genres",[40791],"name"]},{"message":null,"pql":["genres",[40794],"name"]},{"message":null,"pql":["genres",[40795],"name"]},{"message":null,"pql":["genres",[40796],"name"]},{"message":null,"pql":["genres",[40797],"name"]},{"message":null,"pql":["genres",[40801],"name"]},{"message":null,"pql":["genres",[40802],"name"]},{"message":null,"pql":["genres",[40803],"name"]},{"message":null,"pql":["genres",[40807],"name"]},{"message":null,"pql":["genres",[40810],"name"]},{"message":null,"pql":["genres",[40811],"name"]},{"message":null,"pql":["genres",[40812],"name"]},{"message":null,"pql":["genres",[40814],"name"]},{"message":null,"pql":["genres",[40818],"name"]},{"message":null,"pql":["genres",[40820],"name"]},{"message":null,"pql":["genres",[40821],"name"]},{"message":null,"pql":["genres",[40825],"name"]},{"message":null,"pql":["genres",[40826],"name"]},{"message":null,"pql":["genres",[40827],"name"]},{"message":null,"pql":["genres",[40828],"name"]},{"message":null,"pql":["genres",[40830],"name"]},{"message":null,"pql":["genres",[40831],"name"]},{"message":null,"pql":["genres",[40832],"name"]},{"message":null,"pql":["genres",[40833],"name"]},{"message":null,"pql":["genres",[40836],"name"]},{"message":null,"pql":["genres",[40837],"name"]},{"message":null,"pql":["genres",[40839],"name"]},{"message":null,"pql":["genres",[40840],"name"]},{"message":null,"pql":["genres",[40842],"name"]},{"message":null,"pql":["genres",[40844],"name"]},{"message":null,"pql":["genres",[40845],"name"]},{"message":null,"pql":["genres",[40847],"name"]},{"message":null,"pql":["genres",[40848],"name"]},{"message":null,"pql":["genres",[40849],"name"]},{"message":null,"pql":["genres",[40853],"name"]},{"message":null,"pql":["genres",[40856],"name"]},{"message":null,"pql":["genres",[40857],"name"]},{"message":null,"pql":["genres",[40858],"name"]},{"message":null,"pql":["genres",[40859],"name"]},{"message":null,"pql":["genres",[40860],"name"]},{"message":null,"pql":["genres",[40864],"name"]},{"message":null,"pql":["genres",[40865],"name"]},{"message":null,"pql":["genres",[40866],"name"]},{"message":null,"pql":["genres",[40867],"name"]},{"message":null,"pql":["genres",[40868],"name"]},{"message":null,"pql":["genres",[40869],"name"]},{"message":null,"pql":["genres",[40870],"name"]},{"message":null,"pql":["genres",[40871],"name"]},{"message":null,"pql":["genres",[40878],"name"]},{"message":null,"pql":["genres",[40883],"name"]},{"message":null,"pql":["genres",[40885],"name"]},{"message":null,"pql":["genres",[40888],"name"]},{"message":null,"pql":["genres",[40889],"name"]},{"message":null,"pql":["genres",[40891],"name"]},{"message":null,"pql":["genres",[40895],"name"]},{"message":null,"pql":["genres",[40896],"name"]},{"message":null,"pql":["genres",[40897],"name"]},{"message":null,"pql":["genres",[40898],"name"]},{"message":null,"pql":["genres",[40899],"name"]},{"message":null,"pql":["genres",[40901],"name"]},{"message":null,"pql":["genres",[40902],"name"]},{"message":null,"pql":["genres",[40903],"name"]},{"message":null,"pql":["genres",[40905],"name"]},{"message":null,"pql":["genres",[40907],"name"]},{"message":null,"pql":["genres",[40908],"name"]},{"message":null,"pql":["genres",[40909],"name"]},{"message":null,"pql":["genres",[40910],"name"]},{"message":null,"pql":["genres",[40912],"name"]},{"message":null,"pql":["genres",[40913],"name"]},{"message":null,"pql":["genres",[40914],"name"]},{"message":null,"pql":["genres",[40916],"name"]},{"message":null,"pql":["genres",[40919],"name"]},{"message":null,"pql":["genres",[40920],"name"]},{"message":null,"pql":["genres",[40921],"name"]},{"message":null,"pql":["genres",[40922],"name"]},{"message":null,"pql":["genres",[40923],"name"]},{"message":null,"pql":["genres",[40924],"name"]},{"message":null,"pql":["genres",[40925],"name"]},{"message":null,"pql":["genres",[40928],"name"]},{"message":null,"pql":["genres",[40930],"name"]},{"message":null,"pql":["genres",[40931],"name"]},{"message":null,"pql":["genres",[40932],"name"]},{"message":null,"pql":["genres",[40933],"name"]},{"message":null,"pql":["genres",[40934],"name"]},{"message":null,"pql":["genres",[40936],"name"]},{"message":null,"pql":["genres",[40938],"name"]},{"message":null,"pql":["genres",[40939],"name"]},{"message":null,"pql":["genres",[40940],"name"]},{"message":null,"pql":["genres",[40941],"name"]},{"message":null,"pql":["genres",[40942],"name"]},{"message":null,"pql":["genres",[40943],"name"]},{"message":null,"pql":["genres",[40945],"name"]},{"message":null,"pql":["genres",[40950],"name"]},{"message":null,"pql":["genres",[40951],"name"]},{"message":null,"pql":["genres",[40953],"name"]},{"message":null,"pql":["genres",[40954],"name"]},{"message":null,"pql":["genres",[40955],"name"]},{"message":null,"pql":["genres",[40957],"name"]},{"message":null,"pql":["genres",[40958],"name"]}]},"paths":[["genres",[39960,39961,39962,39963,39964,39965,39966,39967,39968,39969,39970,39971,39972,39973,39974,39975,39976,39977,39978,39979,39980,39981,39982,39983,39984,39985,39986,39987,39988,39989,39990,39991,39992,39993,39994,39995,39996,39997,39998,39999,40000,40001,40002,40003,40004,40005,40006,40007,40008,40009,40010,40011,40012,40013,40014,40015,40016,40017,40018,40019,40020,40021,40022,40023,40024,40025,40026,40027,40028,40029,40030,40031,40032,40033,40034,40035,40036,40037,40038,40039,40040,40041,40042,40043,40044,40045,40046,40047,40048,40049,40050,40051,40052,40053,40054,40055,40056,40057,40058,40059,40060,40061,40062,40063,40064,40065,40066,40067,40068,40069,40070,40071,40072,40073,40074,40075,40076,40077,40078,40079,40080,40081,40082,40083,40084,40085,40086,40087,40088,40089,40090,40091,40092,40093,40094,40095,40096,40097,40098,40099,40100,40101,40102,40103,40104,40105,40106,40107,40108,40109,40110,40111,40112,40113,40114,40115,40116,40117,40118,40119,40120,40121,40122,40123,40124,40125,40126,40127,40128,40129,40130,40131,40132,40133,40134,40135,40136,40137,40138,40139,40140,40141,40142,40143,40144,40145,40146,40147,40148,40149,40150,40151,40152,40153,40154,40155,40156,40157,40158,40159,40160,40161,40162,40163,40164,40165,40166,40167,40168,40169,40170,40171,40172,40173,40174,40175,40176,40177,40178,40179,40180,40181,40182,40183,40184,40185,40186,40187,40188,40189,40190,40191,40192,40193,40194,40195,40196,40197,40198,40199,40200,40201,40202,40203,40204,40205,40206,40207,40208,40209,40210,40211,40212,40213,40214,40215,40216,40217,40218,40219,40220,40221,40222,40223,40224,40225,40226,40227,40228,40229,40230,40231,40232,40233,40234,40235,40236,40237,40238,40239,40240,40241,40242,40243,40244,40245,40246,40247,40248,40249,40250,40251,40252,40253,40254,40255,40256,40257,40258,40259,40260,40261,40262,40263,40264,40265,40266,40267,40268,40269,40270,40271,40272,40273,40274,40275,40276,40277,40278,40279,40280,40281,40282,40283,40284,40285,40286,40287,40288,40289,40290,40291,40292,40293,40294,40295,40296,40297,40298,40299,40300,40301,40302,40303,40304,40305,40306,40307,40308,40309,40310,40311,40312,40313,40314,40315,40316,40317,40318,40319,40320,40321,40322,40323,40324,40325,40326,40327,40328,40329,40330,40331,40332,40333,40334,40335,40336,40337,40338,40339,40340,40341,40342,40343,40344,40345,40346,40347,40348,40349,40350,40351,40352,40353,40354,40355,40356,40357,40358,40359,40360,40361,40362,40363,40364,40365,40366,40367,40368,40369,40370,40371,40372,40373,40374,40375,40376,40377,40378,40379,40380,40381,40382,40383,40384,40385,40386,40387,40388,40389,40390,40391,40392,40393,40394,40395,40396,40397,40398,40399,40400,40401,40402,40403,40404,40405,40406,40407,40408,40409,40410,40411,40412,40413,40414,40415,40416,40417,40418,40419,40420,40421,40422,40423,40424,40425,40426,40427,40428,40429,40430,40431,40432,40433,40434,40435,40436,40437,40438,40439,40440,40441,40442,40443,40444,40445,40446,40447,40448,40449,40450,40451,40452,40453,40454,40455,40456,40457,40458,40459,40460,40461,40462,40463,40464,40465,40466,40467,40468,40469,40470,40471,40472,40473,40474,40475,40476,40477,40478,40479,40480,40481,40482,40483,40484,40485,40486,40487,40488,40489,40490,40491,40492,40493,40494,40495,40496,40497,40498,40499,40500,40501,40502,40503,40504,40505,40506,40507,40508,40509,40510,40511,40512,40513,40514,40515,40516,40517,40518,40519,40520,40521,40522,40523,40524,40525,40526,40527,40528,40529,40530,40531,40532,40533,40534,40535,40536,40537,40538,40539,40540,40541,40542,40543,40544,40545,40546,40547,40548,40549,40550,40551,40552,40553,40554,40555,40556,40557,40558,40559,40560,40561,40562,40563,40564,40565,40566,40567,40568,40569,40570,40571,40572,40573,40574,40575,40576,40577,40578,40579,40580,40581,40582,40583,40584,40585,40586,40587,40588,40589,40590,40591,40592,40593,40594,40595,40596,40597,40598,40599,40600,40601,40602,40603,40604,40605,40606,40607,40608,40609,40610,40611,40612,40613,40614,40615,40616,40617,40618,40619,40620,40621,40622,40623,40624,40625,40626,40627,40628,40629,40630,40631,40632,40633,40634,40635,40636,40637,40638,40639,40640,40641,40642,40643,40644,40645,40646,40647,40648,40649,40650,40651,40652,40653,40654,40655,40656,40657,40658,40659,40660,40661,40662,40663,40664,40665,40666,40667,40668,40669,40670,40671,40672,40673,40674,40675,40676,40677,40678,40679,40680,40681,40682,40683,40684,40685,40686,40687,40688,40689,40690,40691,40692,40693,40694,40695,40696,40697,40698,40699,40700,40701,40702,40703,40704,40705,40706,40707,40708,40709,40710,40711,40712,40713,40714,40715,40716,40717,40718,40719,40720,40721,40722,40723,40724,40725,40726,40727,40728,40729,40730,40731,40732,40733,40734,40735,40736,40737,40738,40739,40740,40741,40742,40743,40744,40745,40746,40747,40748,40749,40750,40751,40752,40753,40754,40755,40756,40757,40758,40759,40760,40761,40762,40763,40764,40765,40766,40767,40768,40769,40770,40771,40772,40773,40774,40775,40776,40777,40778,40779,40780,40781,40782,40783,40784,40785,40786,40787,40788,40789,40790,40791,40792,40793,40794,40795,40796,40797,40798,40799,40800,40801,40802,40803,40804,40805,40806,40807,40808,40809,40810,40811,40812,40813,40814,40815,40816,40817,40818,40819,40820,40821,40822,40823,40824,40825,40826,40827,40828,40829,40830,40831,40832,40833,40834,40835,40836,40837,40838,40839,40840,40841,40842,40843,40844,40845,40846,40847,40848,40849,40850,40851,40852,40853,40854,40855,40856,40857,40858,40859,40860,40861,40862,40863,40864,40865,40866,40867,40868,40869,40870,40871,40872,40873,40874,40875,40876,40877,40878,40879,40880,40881,40882,40883,40884,40885,40886,40887,40888,40889,40890,40891,40892,40893,40894,40895,40896,40897,40898,40899,40900,40901,40902,40903,40904,40905,40906,40907,40908,40909,40910,40911,40912,40913,40914,40915,40916,40917,40918,40919,40920,40921,40922,40923,40924,40925,40926,40927,40928,40929,40930,40931,40932,40933,40934,40935,40936,40937,40938,40939,40940,40941,40942,40943,40944,40945,40946,40947,40948,40949,40950,40951,40952,40953,40954,40955,40956,40957,40958],"name"]]}
